conductor/__init__.py
conductor/cli.py
conductor/core/__init__.py
conductor/core/__version__.py
conductor/core/api_client.py
conductor/core/client_db.py
conductor/core/common.py
conductor/core/conductor_submit.py
conductor/core/data_block.py
conductor/core/downloader.py
conductor/core/downloader2.py
conductor/core/exceptions.py
conductor/core/expander.py
conductor/core/file_utils.py
conductor/core/gpath.py
conductor/core/gpath_list.py
conductor/core/loggeria.py
conductor/core/package_environment.py
conductor/core/package_tree.py
conductor/core/package_utils.py
conductor/core/pyside_utils.py
conductor/core/sequence.py
conductor/core/submitter.py
conductor/core/submitter_resources.py
conductor/core/submitter_resources.qrc
conductor/core/uploader.py
conductor/core/uploader_v2.py
conductor/core/version_check.py
conductor/core/worker.py
conductor/core/auth/__init__.py
conductor/core/auth/server.py
conductor/core/auth/resources/index.html
conductor/core/lsseq/PKG-INFO
conductor/core/lsseq/README
conductor/core/lsseq/__init__.py
conductor/core/lsseq/condenseseq
conductor/core/lsseq/expandseq
conductor/core/lsseq/lsseq
conductor/core/lsseq/seqLister.py
conductor/core/lsseq/setup.py
conductor/core/resources/arrow_refresh_x16.png
conductor/core/resources/checkbox_off_redx_8x7.png
conductor/core/resources/checkbox_off_redx_disabled_8x7.png
conductor/core/resources/checkbox_on_greenx_8x7.png
conductor/core/resources/checkbox_on_greenx_disabled_8x7.png
conductor/core/resources/conductor_logo_01_x32.png
conductor/core/resources/conductor_logo_red_w_title_x64.png
conductor/core/resources/conductor_logo_white.png
conductor/core/resources/conductor_logo_white.qrc
conductor/core/resources/conductor_logo_white.svg
conductor/core/resources/conductor_logo_white_100.png
conductor/core/resources/conductor_logo_white_150.png
conductor/core/resources/conductor_logo_white_200.png
conductor/core/resources/resources.yml
conductor/core/resources/submitter.ui
conductor.core-0.1.0.dist-info/METADATA
conductor.core-0.1.0.dist-info/WHEEL
conductor.core-0.1.0.dist-info/entry_points.txt
conductor.core-0.1.0.dist-info/top_level.txt
conductor.core-0.1.0.dist-info/RECORD
