Metadata-Version: 2.1
Name: conductor.core
Version: 0.1.0
Summary: Core functionality for Conductor's client tools
Home-page: https://github.com/AtomicConductor/conductor-core
Author: conductor
Author-email: info@conductortech.com
License: UNKNOWN
Platform: UNKNOWN
Classifier: Operating System :: OS Independent
Classifier: Programming Language :: Python :: 2.7
Classifier: Programming Language :: Python
Classifier: Topic :: Multimedia :: Graphics :: 3D Rendering
Requires-Python: ~=2.7
Requires-Dist: pyjwt (>=1.4.2)
Requires-Dist: pyyaml (>=3.11)
Requires-Dist: qt.py (>=1.1.0)
Requires-Dist: requests (>=2.10.0)
